tweetScraping/__init__.py
tweetScraping/tweetScraping.py
tweetScraping-1.0.2.dist-info/LICENSE
tweetScraping-1.0.2.dist-info/METADATA
tweetScraping-1.0.2.dist-info/WHEEL
tweetScraping-1.0.2.dist-info/top_level.txt
tweetScraping-1.0.2.dist-info/RECORD
