Metadata-Version: 2.1
Name: tweetScraping
Version: 1.0.2
Summary: A Python Package to get tweets with giving only single keyword
Home-page: UNKNOWN
Author: Amit Kumar Kushwaha, Subhankar Saha
Author-email: kushwaha.amitkumar@gmail.com, subhankarsaha2410@gmail.com
License: MIT
Keywords: python,tweet scraping,twitter,scraping
Platform: UNKNOWN
Classifier: License :: OSI Approved :: MIT License
Classifier: Development Status :: 5 - Production/Stable
Classifier: Intended Audience :: Developers
Classifier: Intended Audience :: Science/Research
Classifier: Programming Language :: Python :: 3
Classifier: Operating System :: OS Independent
Requires-Dist: pandas
Requires-Dist: numpy
Requires-Dist: tweepy
Requires-Dist: nltk
Requires-Dist: holidays
Requires-Dist: textblob
